mercapi/__init__.py
mercapi/mapping/__init__.py
mercapi/mapping/definitions.py
mercapi/mercapi.py
mercapi/models/__init__.py
mercapi/models/base.py
mercapi/models/common.py
mercapi/models/item/__init__.py
mercapi/models/item/data.py
mercapi/models/item/item.py
mercapi/models/profile/__init__.py
mercapi/models/profile/items.py
mercapi/models/profile/profile.py
mercapi/models/search/__init__.py
mercapi/models/search/meta.py
mercapi/models/search/search_result_item.py
mercapi/models/search/search_results.py
mercapi/requests/__init__.py
mercapi/requests/base.py
mercapi/requests/search.py
mercapi/util/__init__.py
mercapi/util/errors.py
mercapi/util/jwt.py
mercapi-0.4.2.dist-info/LICENSE
mercapi-0.4.2.dist-info/METADATA
mercapi-0.4.2.dist-info/WHEEL
mercapi-0.4.2.dist-info/RECORD
