Metadata-Version: 2.1
Name: mercapi
Version: 0.4.2
Summary: Python API for querying and browsing mercari.jp
Home-page: https://github.com/take-kun/mercapi/
License: MIT
Keywords: api,scraping
Author: take-kun
Author-email: 109226194+take-kun@users.noreply.github.com
Requires-Python: >=3.9,<4.0
Classifier: License :: OSI Approved :: MIT License
Classifier: Programming Language :: Python :: 3
Classifier: Programming Language :: Python :: 3.9
Classifier: Programming Language :: Python :: 3.10
Classifier: Programming Language :: Python :: 3.11
Classifier: Programming Language :: Python :: 3.12
Classifier: Programming Language :: Python :: 3.13
Requires-Dist: ecdsa (>=0.19.0,<0.20.0)
Requires-Dist: httpx (>=0.27.2,<0.28.0)
Requires-Dist: python-jose[cryptography] (>=3.3.0,<4.0.0)
Project-URL: Repository, https://github.com/take-kun/mercapi/
